pytaskmgr/__init__.py
pytaskmgr/process.py
pytaskmgr/system.py
PyTaskMGR-0.1.1.dist-info/METADATA
PyTaskMGR-0.1.1.dist-info/WHEEL
PyTaskMGR-0.1.1.dist-info/top_level.txt
PyTaskMGR-0.1.1.dist-info/RECORD
