Metadata-Version: 2.1
Name: PyTaskMGR
Version: 0.1.1
Summary: A Python library to manage system processes and gather system information.
Home-page: https://github.com/PolishBoiYT/PyTaskMGR
Author: PolishBoiYT
Author-email: polishboiyt@example.com
Classifier: Programming Language :: Python :: 3
Classifier: License :: OSI Approved :: MIT License
Classifier: Operating System :: OS Independent
Requires-Python: >=3.6
Requires-Dist: psutil
